flask_app/SCDB_ML_app.py
flask_app/__init__.py
flask_app/mine_decision_tree.py
flask_app/predict_decision_tree.py
flask_app/train_decision_tree.py
scdb_ml_app/SCDB_ML_app.py
scdb_ml_app/__init__.py
scdb_ml_app/decomposing_temporal_series.py
scdb_ml_app/mine_decision_tree.py
scdb_ml_app/mining_temporal_series.py
scdb_ml_app/predict_decision_tree.py
scdb_ml_app/predict_naive_bayes.py
scdb_ml_app/train_decision_tree.py
scdb_ml_app/train_naive_bayes.py
scdb_ml_app/models/SCDB_2023_01_justiceCentered_Citation.csv.zip
scdb_ml_app/models/__init__.py
scdb_ml_app/models/accuracy_naive_bayes.txt
scdb_ml_app/models/accuracy_tree.txt
scdb_ml_app/models/decision_naive_bayes.pkl
scdb_ml_app/models/decision_tree_model.pkl
scdb_ml_app/models/predicted_decisionDirection.csv
scdb_ml_app/models/preprocessed_decision_tree.csv
scdb_ml_app/models/temporal_series_image.png
scdb_ml_app/models/temporal_series_with_mean.csv
scdb_ml_app/models/SCDB_2023_01_justiceCentered_Citation/SCDB_2023_01_justiceCentered_Citation.csv
scdb_ml_app/static/__init__.py
scdb_ml_app/static/icon/404-error-template-3.webp
scdb_ml_app/static/icon/__init__.py
scdb_ml_app/static/icon/data-science.png
scdb_ml_app/static/icon/error.png
scdb_ml_app/static/icon/mining_ml.png
scdb_ml_app/static/icon/ml.png
scdb_ml_app/static/icon/save.png
scdb_ml_app/static/icon/subplot_figure.html
scdb_ml_app/static/icon/temporal_series_image.png
scdb_ml_app/static/js/__init__.py
scdb_ml_app/static/js/create_model.js
scdb_ml_app/static/js/mining_all.js
scdb_ml_app/static/js/mining_tree.js
scdb_ml_app/static/js/to_train_tree.js
scdb_ml_app/static/js/training_all.js
scdb_ml_app/static/js/training_tree.js
scdb_ml_app/static/styles/__init__.py
scdb_ml_app/static/styles/main.css
scdb_ml_app/templates/__init__.py
scdb_ml_app/templates/base.html
scdb_ml_app/templates/index.html
scdb_ml_app/templates/mine_all.html
scdb_ml_app/templates/mine_tree.html
scdb_ml_app/templates/notFound.html
scdb_ml_app/templates/predict_base.html
SCDB_ML_app-1.3.1.dist-info/LICENSE.txt
SCDB_ML_app-1.3.1.dist-info/METADATA
SCDB_ML_app-1.3.1.dist-info/WHEEL
SCDB_ML_app-1.3.1.dist-info/licenseheader.txt
SCDB_ML_app-1.3.1.dist-info/top_level.txt
SCDB_ML_app-1.3.1.dist-info/RECORD
